{
  "id": "12",
  "stream": "electronics-and-communication-engineering",
  "packet": "2022",
  "year": "2022",
  "type": "MCQ",
  "key": "B\n\nGATE 2022 \n [Forenoon Session]\nElectronics & Communication Engineering\nPAGE\n12",
  "question_text": "Question 12 \n \n \nMathematics\nConsider a system of linear equations \nAx\nb\n\uf03d\n, where\n1\n2\n3\nA\n\uf0e9\n\uf0f9\n\uf02d\n\uf03d\uf0ea\n\uf0fa\n\uf02d\n\uf02d\n\uf0ea\n\uf0fa\n\uf0eb\n\uf0fb\n3\nb\n\uf0e9\uf0f9\n\uf03d\uf0ea\uf0fa\n\uf0eb\uf0fb\n, \n1\n1\n2\n3\n\nThis system of equations admits\n(A) a unique solution for \nx\n \n(B) No solutions for \nx\n(C) exactly two solutions for \nx\n \n(D) infinitely many solutions for \nx",
  "answer_text": "B\n\nGATE 2022 \n [Forenoon Session]\nElectronics & Communication Engineering\nPAGE\n12",
  "explanation_text": "Sol.\n \nSystem of linear equation, \nAx\nb\n\uf03d\n\uf0e9\n\uf0f9\n\uf02d\n\uf0e9\uf0f9\n\uf03d\n\uf03d\n\uf0ea\n\uf0fa\n\uf0ea\uf0fa\n\uf02d\n\uf02d\n\uf0eb\uf0fb\n\uf0ea\n\uf0fa\n\uf0eb\n\uf0fb\n1\n2\n3\n1\n,\n3\n1\n2\n3\nA\nb\nGiven matrix,\n\n\uf0b4\n2 3\n\uf0e9\n\uf0f9\n\uf02d\n\uf03d\n\uf03d\uf0ea\n\uf0fa\n\uf02d\n\uf02d\n\uf0ea\n\uf0fa\n\uf0eb\n\uf0fb\n1\n2\n3\n: 1\n:\n1\n2\n3 :\n3\nC\nA b\nAugmented matrix, \n\uf05b\n\uf05d\n\n\uf0b4\n2 4\n2\n2\n1\nR\nR\nR\n\uf0ae\n\uf02b\n,\n\uf0e9\n\uf0f9\n\uf02d\n\uf03d\uf0ea\n\uf0fa\n\uf0eb\n\uf0fb\n1\n2\n3 :\n1\n0\n0\n0 :\n4\nC\n\n\n\uf0b4\n2 4\nWe can see that, of the above augmented matrix.\nMatrix \nA\n has only one linearly independent row, \n( )\n1\nA\n\uf072\n\uf03d\nand matrix \n\uf05b\n\uf05d\n:\nA b\n  has two linearly independent rows\n( : )\n2\nA b\n\uf072\n\uf03d\nHere, \n( )\n( : )\nA\nA b\n\uf072\n\uf0b9\uf072\nSo, system has no solution for \nx\n.\nHence, the correct option is (B)."
}