{
  "id": "53",
  "stream": "chemical-engineering",
  "packet": "2024",
  "year": "2024",
  "type": "MCQ",
  "key": "18.1 to 18.3",
  "question_text": "Question 53\nConsider the function \n\ud835\udc53(\ud835\udc65, \ud835\udc66, \ud835\udc67) = \ud835\udc65\n4\n \n+ 2\ud835\udc66\n3\n \n+ \ud835\udc67\n2\n.  The directional derivative of the function at the point \n\ud835\udc43(\u22121,1, \u22121)\n along \n(\ud835\udc56\u0302 + \ud835\udc57\u0302)\n, where \n\ud835\udc56\u0302\n and \n\ud835\udc57\u0302\n are unit vectors in the \n\ud835\udc65\n and \n\ud835\udc66\n directions, respectively, rounded \noff to 2 decimal places, is _______.\n[Engineering Mathematics, Vector Calculus]\n (2 Marks)\n \nAns. \n1.39 to 1.43 \nSol.\n \nGiven :\n\ud835\udc53(\ud835\udc65, \ud835\udc66, \ud835\udc67) = \ud835\udc65\n4\n \n+ 2\ud835\udc66\n3\n \n+ \ud835\udc67\n2\n\ud835\udc4e\u20d7= \ud835\udc56\u0302 + \ud835\udc57\u0302\n \n \nGradient of function \nf\n is given by,\n\ud835\udf15\ud835\udc53\n\ud835\udf15\ud835\udc53\n\ud835\udf15\ud835\udc53\n\ud835\udf15\ud835\udc67\n\ud835\udc58\u0302\n\ud835\udefb\ud835\udc53=\n\ud835\udf15\ud835\udc65\n\ud835\udc56\u0302 +\n\ud835\udf15\ud835\udc66\n\ud835\udc57\u0302 +\n\ud835\udefb\ud835\udc53= 4\ud835\udc65\n3\n\ud835\udc56\u0302 + 6\ud835\udc66\n2\n\ud835\udc57\u0302 + 2\ud835\udc67\ud835\udc58\n\u0302\n \n \nAt point (\u20131, 1, \u20131)\n\ud835\udefb\ud835\udc53|\n(\u22121,1,\u22121)\n = \u22124\ud835\udc56\u0302 + 6\ud835\udc57\u0302 \u22122\ud835\udc58\n\u0302\nUnit normal vector is given by,\n\ud835\udc4e\u20d7\u20d7\n\ud835\udc4e\u0302 =\n|\ud835\udc4e\u20d7\u20d7|\nDirectional derivative of \nf\n along \n(\ud835\udc4e\u20d7)\n is given by,\n\ud835\udc37\ud835\udc37= \ud835\udefb\u22c5\ud835\udc53|\n\ud835\udc43\n\u22c5\ud835\udc4e\u0302\nGiven \n\ud835\udc4e\u20d7= \ud835\udc56\u0302 + \ud835\udc57\u0302\n|\ud835\udc4e\u20d7| = \u221a1\n2\n \n+ 1\n2\n \n= \u221a2\n\ud835\udc56\u0302+\ud835\udc57\u0302\n\ud835\udc4e\u0302 =\n\u221a2\n\ud835\udc56\u0302\n\ud835\udc57\u0302\n\ud835\udc37\ud835\udc37= (\u22124\ud835\udc56\u0302 + 6\ud835\udc57\u0302 \u22122\ud835\udc58\n\u0302\n) \u22c5(\n\u221a2\n)\n\u221a2\n \n+\n\nPAGE\n49\n\n\u22124\n6\n2\n\ud835\udc37\ud835\udc37=\n\u221a2\n \n= \u221a2 = 1.414\n\u221a2\n \n+\n\u221a2\n \n=\nHence, the directional derivative of the function at the point \n\ud835\udc43(\u22121,1, \u22121)\n along \n(\ud835\udc56\u0302 + \ud835\udc57\u0302)\n is 1.41 \nQuestion 54\n \n \nConsider the process in the figure for manufacturing \n\ud835\udc35\n.  The feed to the process is 90 mol% \n\ud835\udc34\n and a close-\nboiling inert component \n\ud835\udc3c\n.  At a particular steady-state : \n \n[Process calculation 2 marks]\n\uf0b7\n \n\ud835\udc35\nproduct rate is \n100kmol\n\u210e\n\u22121\n \n\uf0b7\n \nSingle-pass conversion of \n\ud835\udc34\n in the reactor is 50% \n\uf0b7\n \nRecycle-to-purge stream flow ratio is 10\nThe flow rate of \n\ud835\udc34\nin the purge stream in \nkmol\n\u210e\n\u22121\n, rounded off to 1 decimal place, is _______.\nFeed\nPurge\n0.9\nA\nx\n \uf03d\n0.1\nI\nx\n \uf03d\n0\nB\nx\n \uf03d\nReactor\n2\nA\nB\n\uf0ae\nSeparator\n\u20131\n \nPure \nB\n1\nB\nx\n \uf03d\nx\ni\ni\n: mole fraction of species\n100 kmol h",
  "answer_text": "18.1 to 18.3",
  "explanation_text": "Sol.\n \nGiven:\nRecycle\nE\nPurge( )\nP\n0\nB\nx\n \uf03d\nP\nA\nx\n200\nA\n \uf03d\n0\nP\nA\nx\n\uf03d\nP\nI\nx\nFeed\n0\nP\nI\nx\n\uf03d\nSeparator\n2\nA\nB\n\uf0ae\nM\n0.9\nA\nx\n\uf03d\n100\nB\n \uf03d\nmixed\n0.1\nI\nx\n \uf03d\n200\nA\n \uf03d\nPure B\n1\nB\nx\n\uf03d\n100 kmol/hr\n\nApplying overall material balance\nF = P + 100  \n \n \n \n \n \n \n\u2026(i)\nApplying inert balance\n\ud835\udc39\n= \ud835\udc43\ud835\udc65\n\ud835\udc3c\n\ud835\udc43\n\ud835\udc39\ud835\udc65\n\ud835\udc3c\n\ud835\udc43\n  \n \n \n \n \n \n\u2026(ii)\n\ud835\udc39\u00d7 0.1 = \ud835\udc43\ud835\udc65\n\ud835\udc3c\n\ud835\udc45\nGiven\n\ud835\udc43\n= 10\nSingle pass Conversion = 0.5\n\nPAGE\n50\n\n\u2235\n \n100 \nKmol/hr\n B react with 200 Kmol/hr A\nBut SPC (Single pass Conversion)  = 0.5\n200\nKmol\n\u2234\n \nA mole in feed \n=\nhr\n0.5\n \n= 400\nAt point m, applying A balance\n\ud835\udc43\n) = 400\n\ud835\udc39\u00d7 0.9 + 10\ud835\udc43(1 \u2212\ud835\udc65\n\ud835\udc3c\n\ud835\udc43\n= 400\n0.9\ud835\udc39+ 10\ud835\udc43\u221210\ud835\udc43\ud835\udc65\n\ud835\udc3c\n0.9\ud835\udc39+ 10\ud835\udc43\u221210 \u00d7 0.1\ud835\udc39= 400\n10\ud835\udc43\u22120.1\ud835\udc39= 400\n \n \n \n \n \n \n\u2026(iii)\n\ud835\udc43\u2212\ud835\udc39= \u2212100\n  Equation (i) \n\u00d7 10\n10\ud835\udc43\u221210\ud835\udc39= \u22121000\n \n \n \n \n \n \n\u2026(iv)\nEquation (iii) \u2013 Equation (iv)\n9.9 F = 1400\n1400\n\ud835\udc39=\n9.9\n \n= 141.414\nFrom Equation (i) F = P +10\n\u2234\n \n\ud835\udc43= 41.44Kmol/hr\nApplying balance on point E(on A Species)\n\ud835\udc43\n+ \ud835\udc43\ud835\udc65\n\ud835\udc34\n\ud835\udc43\n200 = \ud835\udc45\ud835\udc65\n\ud835\udc34\n\ud835\udc43\n200 = 11\ud835\udc43\ud835\udc65\n\ud835\udc34\n\ud835\udc43\n= 18.18\n\ud835\udc43\ud835\udc65\n\ud835\udc34"
}