{
  "id": "24",
  "stream": "chemical-engineering",
  "packet": "2023",
  "year": "2023",
  "type": "MCQ",
  "key": "(C) \nSol. \nVolumetric flow rate of the liquid is measured by rotameter.",
  "question_text": "Question 24 \n \nWhich one of the following quantities of a flowing fluid is measured using a rotameter?\n[Fluid Mechanics, 1 Mark]\n \n \n(A) Static pressure \n \n(B) Dynamic pressure \n \n(C) Volumetric flow rate \n \n(D) Viscosity",
  "answer_text": "(C) \nSol. \nVolumetric flow rate of the liquid is measured by rotameter.",
  "explanation_text": ""
}