{
  "id": "37",
  "stream": "civil-engineering",
  "packet": "2020-N",
  "year": "2020",
  "type": "MCQ",
  "key": "257.36",
  "question_text": "Question\n 37\nA  theodolite is set up at station A. The  RL of  instrument axis is 212.250 m. The angle of elevation to \nthe top of a 4 m long staff, held vertical at station B, is \n0\n7\n . The horizontal distance between stations A \nand B is 400 m Neglecting the errors due to curvature of earth and refraction, the RL (in m\n, round off to \nthree decimal places\n) of station B is _______.",
  "answer_text": "257.36",
  "explanation_text": ""
}